hepdata_validator/__init__.py
hepdata_validator/cli.py
hepdata_validator/data_file_validator.py
hepdata_validator/full_submission_validator.py
hepdata_validator/schema_downloader.py
hepdata_validator/schema_resolver.py
hepdata_validator/submission_file_validator.py
hepdata_validator/version.py
hepdata_validator/schemas/0.1.0/additional_info_schema.json
hepdata_validator/schemas/0.1.0/data_schema.json
hepdata_validator/schemas/0.1.0/submission_schema.json
hepdata_validator/schemas/1.0.0/additional_info_schema.json
hepdata_validator/schemas/1.0.0/data_schema.json
hepdata_validator/schemas/1.0.0/submission_schema.json
hepdata_validator/schemas/1.0.1/additional_info_schema.json
hepdata_validator/schemas/1.0.1/data_schema.json
hepdata_validator/schemas/1.0.1/submission_schema.json
hepdata_validator/schemas/1.1.0/additional_info_schema.json
hepdata_validator/schemas/1.1.0/additional_resources_schema.json
hepdata_validator/schemas/1.1.0/data_schema.json
hepdata_validator/schemas/1.1.0/submission_schema.json
hepdata_validator/schemas/1.1.1/additional_info_schema.json
hepdata_validator/schemas/1.1.1/additional_resources_schema.json
hepdata_validator/schemas/1.1.1/data_schema.json
hepdata_validator/schemas/1.1.1/submission_schema.json
hepdata_validator-0.3.6.dist-info/LICENSE.txt
hepdata_validator-0.3.6.dist-info/METADATA
hepdata_validator-0.3.6.dist-info/WHEEL
hepdata_validator-0.3.6.dist-info/entry_points.txt
hepdata_validator-0.3.6.dist-info/top_level.txt
hepdata_validator-0.3.6.dist-info/RECORD
