Metadata-Version: 2.1
Name: hepdata-validator
Version: 0.3.6
Summary: JSON schema and validation code for HEPData submissions
Home-page: https://github.com/hepdata/hepdata-validator
Author: HEPData Team
Author-email: info@hepdata.net
License: GPLv2
Keywords: hepdata validator
Platform: any
Requires-Python: >=3.6
License-File: LICENSE.txt
Requires-Dist: click
Requires-Dist: jsonschema
Requires-Dist: packaging
Requires-Dist: pyyaml>=5.4.1
Requires-Dist: requests
Provides-Extra: all
Requires-Dist: Sphinx>7; extra == "all"
Requires-Dist: pytest>=2.7.0; extra == "all"
Requires-Dist: pytest-cache>=1.0; extra == "all"
Requires-Dist: pytest-cov>=1.8.0; extra == "all"
Requires-Dist: pytest-pep8>=1.0.6; extra == "all"
Requires-Dist: coverage>=3.7.1; extra == "all"
Requires-Dist: mock>=2.0.0; extra == "all"
Provides-Extra: docs
Requires-Dist: Sphinx>7; extra == "docs"
Provides-Extra: tests
Requires-Dist: pytest>=2.7.0; extra == "tests"
Requires-Dist: pytest-cache>=1.0; extra == "tests"
Requires-Dist: pytest-cov>=1.8.0; extra == "tests"
Requires-Dist: pytest-pep8>=1.0.6; extra == "tests"
Requires-Dist: coverage>=3.7.1; extra == "tests"
Requires-Dist: mock>=2.0.0; extra == "tests"
